{
  "cwd": "C:\\Users\\Ahri\\Desktop\\EKmaps",
  "type": [
    "cordova"
  ],
  "name": "EKmaps",
  "pkg": "io.framework7.ekmaps",
  "framework": "core",
  "template": "single-view",
  "bundler": "webpack",
  "cssPreProcessor": false,
  "cordova": {
    "folder": "cordova",
    "platforms": [
      "ios",
      "android"
    ],
    "plugins": [
      "cordova-plugin-statusbar",
      "cordova-plugin-keyboard",
      "cordova-plugin-splashscreen"
    ]
  },
  "webpack": {
    "developmentSourceMap": true,
    "productionSourceMap": true,
    "hashAssets": false,
    "preserveAssetsPaths": false,
    "inlineAssets": true
  },
  "theming": {
    "customColor": false,
    "color": "#007aff",
    "darkTheme": false,
    "iconFonts": true,
    "fillBars": false
  },
  "customBuild": false
}